quantplay_mcp/__init__.py
quantplay_mcp/__main__.py
quantplay_mcp/client.py
quantplay_mcp/config.py
quantplay_mcp/models.py
quantplay_mcp/server.py
quantplay_mcp-0.1.22.dist-info/METADATA
quantplay_mcp-0.1.22.dist-info/WHEEL
quantplay_mcp-0.1.22.dist-info/entry_points.txt
quantplay_mcp-0.1.22.dist-info/top_level.txt
quantplay_mcp-0.1.22.dist-info/RECORD
