Metadata-Version: 2.4
Name: quantplay-mcp
Version: 0.1.22
Summary: Quantplay MCP Server
Requires-Python: >=3.11
Requires-Dist: mcp[cli]>=1.6.0
